biosignal_quality/__init__.py
biosignal_quality/biosignal_quality.py
biosignal_quality-0.1.1.dist-info/METADATA
biosignal_quality-0.1.1.dist-info/WHEEL
biosignal_quality-0.1.1.dist-info/top_level.txt
biosignal_quality-0.1.1.dist-info/RECORD
