Metadata-Version: 2.4
Name: biosignal_quality
Version: 0.1.1
Summary: A toolkit for analyzing, assessing, and visualizing biosignal quality
Home-page: https://github.com/barthwalsaurabh0/biosignal_quality
Author: Saurabh Barthwal
Project-URL: Bug Tracker, https://github.com/barthwalsaurabh0/biosignal_quality/issues
Classifier: Programming Language :: Python :: 3
Classifier: License :: OSI Approved :: MIT License
Classifier: Operating System :: OS Independent
Classifier: Topic :: Scientific/Engineering :: Medical Science Apps.
Classifier: Topic :: Scientific/Engineering :: Bio-Informatics
Requires-Python: >=3.7
Requires-Dist: pandas
Requires-Dist: numpy
Requires-Dist: plotly
Requires-Dist: dash
